{
	"backtraceGraph" : 
	{
		"commands" : 
		[
			"install"
		],
		"files" : 
		[
			"extern/rml_ui/Source/Core/CMakeLists.txt"
		],
		"nodes" : 
		[
			{
				"file" : 0
			},
			{
				"command" : 0,
				"file" : 0,
				"line" : 470,
				"parent" : 0
			}
		]
	},
	"installers" : 
	[
		{
			"backtrace" : 1,
			"component" : "Unspecified",
			"destination" : "lib",
			"paths" : 
			[
				"rmlui.lib"
			],
			"targetId" : "rmlui_core::@a34cfabcfda8afb4e3e0",
			"targetIndex" : 13,
			"type" : "target"
		}
	],
	"paths" : 
	{
		"build" : "extern/rml_ui/Source/Core",
		"source" : "extern/rml_ui/Source/Core"
	}
}
